{
  "product": "Nike Air Force 1",
  "product_id": 1,
  "country": "United States",
  "country_id": 1,
  "country_code": "US",
  "value": 130.0,
  "currency": "USD",
  "exchange_rate": 1.0,
  "usd_value": 130.0,
  "description": "Updated manual price for Nike Air Force 1 in US",
  "image_url": "https://static.nike.com/a/images/t_PDP_1280_v1/f_auto,q_auto:eco/b7d9211c-26e7-431a-ac24-b0540fb3c00f/air-force-1-07-mens-shoes-5QFp5Z.png",
  "source_type": "manual",
  "date": "2025-04-12T19:39:56.070017",
  "timestamp": "2025-04-12T19:39:56.072084"
}